linalg_deluxe/__init__.py
linalg_deluxe/linalg_deluxe.py
linalg_deluxe-0.1.3.dist-info/LICENSE
linalg_deluxe-0.1.3.dist-info/METADATA
linalg_deluxe-0.1.3.dist-info/WHEEL
linalg_deluxe-0.1.3.dist-info/top_level.txt
linalg_deluxe-0.1.3.dist-info/RECORD
