Metadata-Version: 2.1
Name: linalg-deluxe
Version: 0.1.3
Summary: Additional linear algebra operations to extend Joel Grus's library from 'Data Science from Scratch' chapter 4
Author-email: Andrew Rose <andrew.rose43@gmail.com>
Project-URL: Homepage, https://github.com/andrewrose43/DataScienceFromScratch_CodeTheBook
Classifier: Programming Language :: Python :: 3
Classifier: License :: OSI Approved :: MIT License
Classifier: Operating System :: OS Independent
Requires-Python: >=3.10
License-File: LICENSE
